additionalFiles.py
toolkitFile.py
toolkitpack-0.0.2.dist-info/LICENSE.txt
toolkitpack-0.0.2.dist-info/METADATA
toolkitpack-0.0.2.dist-info/WHEEL
toolkitpack-0.0.2.dist-info/top_level.txt
toolkitpack-0.0.2.dist-info/RECORD
