Metadata-Version: 2.1
Name: toolkitpack
Version: 0.0.2
Summary: Random operations who cares
Home-page: https://github.com/asishRye/package
Author: Asish Binu Mathew
Author-email: asish+pypi@accubits.com
License: UNKNOWN
Platform: UNKNOWN
Classifier: Programming Language :: Python :: 3.8
Classifier: Programming Language :: Python :: 3.7
Requires-Dist: blessings (==1.7)
